<?xml version="1.0"?>

<tryton>
    <data>        
        
        <!--Forzar borrado Prestamos-->
        <record model="ir.action.wizard" id="act_staff_loan_force_draft">
            <field name="name">Loan Force Draft</field>
            <field name="wiz_name">staff.loan.force_draft</field>
        </record>
        <record model="ir.action.keyword" id="action_staff_loan_force_draft_keyword">
            <field name="keyword">form_action</field>
            <field name="model">staff.loan,-1</field>
            <field name="action" ref="act_staff_loan_force_draft"/>
        </record>

    </data>
</tryton>